adrcommon/__init__.py
adrcommon/constants.py
adrcommon/graph.py
adrcommon/datastore/__init__.py
adrcommon/datastore/datastore.py
adrcommon/datastore/dynamodbstore.py
adrcommon/datastore/memorystore.py
adrcommon/datastore/mongodbstore.py
adrcommon/datastore/ndjsonstore.py
adrcommon/lm/__init__.py
adrcommon/lm/inference.py
adrcommon/lm/lm_provider.py
adrcommon/query/__init__.py
adrcommon/query/query.py
adrcommon/secrets/__init__.py
adrcommon/secrets/provider.py
adrcommon/state/__init__.py
adrcommon/state/stateengine.py
adrcommon/utils/__init__.py
adrcommon/utils/argparser.py
adrcommon/utils/bootstrapper.py
adrcommon/utils/cglobals.py
adrcommon/utils/config.py
adrcommon/utils/maputil.py
adrcommon/utils/timeutil.py
adrcommon/utils/util.py
adrcommon/utils/uuid.py
adrcommon/web/__init__.py
adrcommon/web/cheroot.py
adrcommon-0.1.3.dist-info/METADATA
adrcommon-0.1.3.dist-info/WHEEL
adrcommon-0.1.3.dist-info/top_level.txt
adrcommon-0.1.3.dist-info/RECORD
